cook.py
chef_bomber-1.0.0.dist-info/METADATA
chef_bomber-1.0.0.dist-info/WHEEL
chef_bomber-1.0.0.dist-info/entry_points.txt
chef_bomber-1.0.0.dist-info/top_level.txt
chef_bomber-1.0.0.dist-info/RECORD
