Metadata-Version: 2.1
Name: chef-bomber
Version: 1.0.0
Summary: A professional cooking-themed number utility tool
Author: Chef Bomber
Author-email: Chef Bomber <your-email@example.com>
Keywords: cooking,utility,tool,chef
Classifier: Programming Language :: Python :: 3
Classifier: License :: OSI Approved :: MIT License
Classifier: Operating System :: OS Independent
Requires-Python: >=3.6
Requires-Dist: requests >=2.25.1
